date_day_estimator/__init__.py
date_day_estimator/date_day_estimator.py
date_day_estimator-0.0.4.dist-info/METADATA
date_day_estimator-0.0.4.dist-info/WHEEL
date_day_estimator-0.0.4.dist-info/top_level.txt
date_day_estimator-0.0.4.dist-info/RECORD
